{
  "284": {
    "class_type": "LoadImage",
    "inputs": {
      "image": "man.png"
    }
  },
  "245": {
    "class_type": "INTConstant",
    "inputs": {
      "value": 832
    }
  },
  "246": {
    "class_type": "INTConstant",
    "inputs": {
      "value": 480
    }
  },
  "281": {
    "class_type": "ImageResizeKJv2",
    "inputs": {
      "image": [
        "284",
        0
      ],
      "width": [
        "245",
        0
      ],
      "height": [
        "246",
        0
      ],
      "upscale_method": "lanczos",
      "keep_proportion": "crop",
      "pad_color": "0, 0, 0",
      "crop_position": "center",
      "divisible_by": 16,
      "device": "cpu"
    }
  },
  "125": {
    "class_type": "LoadAudio",
    "inputs": {
      "audio": "man.mp3"
    }
  },
  "129": {
    "class_type": "WanVideoVAELoader",
    "inputs": {
      "model_name": "Wan2_1_VAE_bf16.safetensors",
      "precision": "bf16",
      "use_cpu_cache": false
    }
  },
  "317": {
    "class_type": "TrimAudioDuration",
    "inputs": {
      "audio": [
        "125",
        0
      ],
      "start_index": 0,
      "duration": 2048
    }
  },
  "241": {
    "class_type": "WanVideoTextEncodeCached",
    "inputs": {
      "model_name": "umt5-xxl-enc-fp8_e4m3fn.safetensors",
      "precision": "bf16",
      "positive_prompt": "A western man stands on stage under dramatic lighting, holding a microphone close to their mouth. Wearing a vibrant red jacket with gold embroidery, the singer is speaking while smoke swirls around them, creating a dynamic and atmospheric scene.",
      "negative_prompt": "Close-up, bright tones, overexposed, static, blurred details, subtitles, style, works, paintings, images, static, overall gray, worst quality, low quality, JPEG compression residue, ugly, incomplete, extra fingers, poorly drawn hands, poorly drawn faces, deformed, disfigured, misshapen limbs, fused fingers, still picture, messy background, three legs, many people in the background, walking backwards",
      "quantization": "fp8_e4m3fn",
      "use_disk_cache": true,
      "device": "gpu"
    }
  },
  "427": {
    "class_type": "FloatConstant",
    "inputs": {
      "value": 1
    }
  },
  "358": {
    "class_type": "WanVideoEncode",
    "inputs": {
      "vae": [
        "129",
        0
      ],
      "image": [
        "357",
        0
      ],
      "enable_vae_tiling": false,
      "tile_x": 272,
      "tile_y": 272,
      "tile_stride_x": 144,
      "tile_stride_y": 128,
      "noise_aug_strength": 0,
      "latent_strength": 1
    }
  },
  "359": {
    "class_type": "ReplaceVideoLatentFrames",
    "inputs": {
      "destination": [
        "327",
        0
      ],
      "source": [
        "358",
        0
      ],
      "index": 0
    }
  },
  "324": {
    "class_type": "WanVideoSamplerv2",
    "inputs": {
      "model": [
        "122",
        0
      ],
      "image_embeds": [
        "345",
        0
      ],
      "scheduler": [
        "325",
        0
      ],
      "text_embeds": [
        "241",
        0
      ],
      "cfg": [
        "427",
        0
      ],
      "seed": 1,
      "force_offload": true,
      "add_noise_to_samples": false
    }
  },
  "438": {
    "class_type": "INTConstant",
    "inputs": {
      "value": 93
    }
  },
  "312": {
    "class_type": "WanVideoEncode",
    "inputs": {
      "vae": [
        "129",
        0
      ],
      "image": [
        "281",
        0
      ],
      "enable_vae_tiling": false,
      "tile_x": 272,
      "tile_y": 272,
      "tile_stride_x": 144,
      "tile_stride_y": 128,
      "noise_aug_strength": 0,
      "latent_strength": 1
    }
  },
  "313": {
    "class_type": "WanVideoDecode",
    "inputs": {
      "vae": [
        "129",
        0
      ],
      "samples": [
        "324",
        0
      ],
      "enable_vae_tiling": false,
      "tile_x": 272,
      "tile_y": 272,
      "tile_stride_x": 144,
      "tile_stride_y": 128,
      "normalization": "default"
    }
  },
  "345": {
    "class_type": "WanVideoLongCatAvatarExtendEmbeds",
    "inputs": {
      "prev_latents": [
        "312",
        0
      ],
      "audio_embeds": [
        "194",
        0
      ],
      "num_frames": [
        "438",
        0
      ],
      "overlap": 1,
      "frames_processed": 0,
      "if_not_enough_audio": "pad_with_start",
      "ref_frame_index": 10,
      "ref_mask_frame_range": 3
    }
  },
  "341": {
    "class_type": "ImageBatchExtendWithOverlap",
    "inputs": {
      "source_images": [
        "344",
        0
      ],
      "new_images": [
        "329",
        0
      ],
      "overlap": [
        "423",
        0
      ],
      "overlap_side": "new_images",
      "overlap_mode": "cut"
    }
  },
  "344": {
    "class_type": "GetImageSizeAndCount",
    "inputs": {
      "image": [
        "313",
        0
      ]
    }
  },
  "357": {
    "class_type": "GetImageRangeFromBatch",
    "inputs": {
      "images": [
        "344",
        0
      ],
      "num_frames": [
        "423",
        0
      ],
      "start_index": -1
    }
  },
  "329": {
    "class_type": "WanVideoDecode",
    "inputs": {
      "vae": [
        "129",
        0
      ],
      "samples": [
        "359",
        0
      ],
      "enable_vae_tiling": false,
      "tile_x": 272,
      "tile_y": 272,
      "tile_stride_x": 144,
      "tile_stride_y": 128,
      "normalization": "default"
    }
  },
  "137": {
    "class_type": "DownloadAndLoadWav2VecModel",
    "inputs": {
      "model": "TencentGameMate/chinese-wav2vec2-base",
      "base_precision": "fp16",
      "load_device": "main_device"
    }
  },
  "423": {
    "class_type": "INTConstant",
    "inputs": {
      "value": 13
    }
  },
  "327": {
    "class_type": "WanVideoSamplerv2",
    "inputs": {
      "model": [
        "122",
        0
      ],
      "image_embeds": [
        "346",
        0
      ],
      "scheduler": [
        "325",
        0
      ],
      "text_embeds": [
        "241",
        0
      ],
      "cfg": [
        "427",
        0
      ],
      "seed": 2,
      "force_offload": true,
      "add_noise_to_samples": false
    }
  },
  "453": {
    "class_type": "VHS_VideoCombine",
    "inputs": {
      "images": [
        "341",
        0
      ],
      "audio": [
        "317",
        0
      ],
      "frame_rate": 16,
      "loop_count": 0,
      "filename_prefix": "adgen_longcat",
      "format": "video/h264-mp4",
      "pingpong": false,
      "save_output": true
    }
  },
  "194": {
    "class_type": "MultiTalkWav2VecEmbeds",
    "inputs": {
      "wav2vec_model": [
        "137",
        0
      ],
      "audio_1": [
        "317",
        0
      ],
      "normalize_loudness": true,
      "num_frames": 1000,
      "fps": 32,
      "audio_scale": 1,
      "audio_cfg_scale": 2,
      "multi_audio_type": "para",
      "add_noise_floor": true,
      "smooth_transients": true
    }
  },
  "134": {
    "class_type": "WanVideoBlockSwap",
    "inputs": {
      "blocks_to_swap": 0,
      "offload_img_emb": false,
      "offload_txt_emb": false,
      "use_non_blocking": false,
      "vace_blocks_to_swap": 0,
      "prefetch_blocks": 1,
      "block_swap_debug": false
    }
  },
  "122": {
    "class_type": "WanVideoModelLoader",
    "inputs": {
      "block_swap_args": [
        "134",
        0
      ],
      "lora": [
        "138",
        0
      ],
      "model": "LongCat/LongCat-Avatar-single_fp8_e4m3fn_scaled_mixed_KJ.safetensors",
      "base_precision": "bf16",
      "quantization": "fp8_e4m3fn_scaled",
      "load_device": "offload_device",
      "attention_mode": "sdpa",
      "rms_norm_function": "default"
    }
  },
  "325": {
    "class_type": "WanVideoSchedulerv2",
    "inputs": {
      "scheduler": "longcat_distill_euler",
      "steps": 12,
      "shift": 12,
      "start_step": 0,
      "end_step": -1,
      "enhance_hf": false
    }
  },
  "346": {
    "class_type": "WanVideoLongCatAvatarExtendEmbeds",
    "inputs": {
      "prev_latents": [
        "324",
        0
      ],
      "audio_embeds": [
        "194",
        0
      ],
      "ref_latent": [
        "312",
        0
      ],
      "num_frames": [
        "438",
        0
      ],
      "overlap": [
        "423",
        0
      ],
      "frames_processed": [
        "344",
        3
      ],
      "if_not_enough_audio": "pad_with_start",
      "ref_frame_index": 10,
      "ref_mask_frame_range": 3
    }
  },
  "138": {
    "class_type": "WanVideoLoraSelect",
    "inputs": {
      "lora": "LongCat_distill_lora_alpha64_bf16.safetensors",
      "strength": 0.9,
      "low_mem_load": false,
      "merge_loras": false
    }
  }
}